RotaryTableDobotDidactech/RotaryTableDobot.py
RotaryTableDobotDidactech/Test.py
RotaryTableDobotDidactech/__init__.py
RotaryTableDobotDidactech-1.4.3.dist-info/METADATA
RotaryTableDobotDidactech-1.4.3.dist-info/WHEEL
RotaryTableDobotDidactech-1.4.3.dist-info/top_level.txt
RotaryTableDobotDidactech-1.4.3.dist-info/RECORD
