Metadata-Version: 2.1
Name: RotaryTableDobotDidactech
Version: 1.4.3
Summary: Rotary table for Dobot, DIDACTECH development
Home-page: 
Author: Walter Becerra
Author-email: becerrawalter20@hotmail.com
